bashlet/__init__.py
bashlet/async_client.py
bashlet/client.py
bashlet/errors.py
bashlet/types.py
bashlet/schemas/__init__.py
bashlet/schemas/json_schema.py
bashlet/schemas/pydantic.py
bashlet/tools/__init__.py
bashlet/tools/anthropic.py
bashlet/tools/generic.py
bashlet/tools/langchain.py
bashlet/tools/mcp.py
bashlet/tools/openai.py
bashlet-1.3.2.dist-info/METADATA
bashlet-1.3.2.dist-info/WHEEL
bashlet-1.3.2.dist-info/RECORD
