Metadata-Version: 2.4
Name: bashlet
Version: 1.3.2
Summary: Python SDK for bashlet sandboxed bash execution - provide bashlet as a tool for AI agents
Project-URL: Homepage, https://github.com/anthropics/bashlet
Project-URL: Repository, https://github.com/anthropics/bashlet
Project-URL: Documentation, https://github.com/anthropics/bashlet#readme
Author: Bashlet Authors
License-Expression: MIT
Keywords: ai-agent,anthropic,bash,bashlet,langchain,mcp,openai,sandbox,shell,tools
Classifier: Development Status :: 4 - Beta
Classifier: Intended Audience :: Developers
Classifier: License :: OSI Approved :: MIT License
Classifier: Programming Language :: Python :: 3
Classifier: Programming Language :: Python :: 3.10
Classifier: Programming Language :: Python :: 3.11
Classifier: Programming Language :: Python :: 3.12
Classifier: Programming Language :: Python :: 3.13
Classifier: Topic :: Software Development :: Libraries :: Python Modules
Classifier: Typing :: Typed
Requires-Python: >=3.10
Provides-Extra: all
Requires-Dist: anthropic>=0.30; extra == 'all'
Requires-Dist: langchain-core>=0.2; extra == 'all'
Requires-Dist: mcp>=1.0; extra == 'all'
Requires-Dist: openai>=1.0; extra == 'all'
Requires-Dist: pydantic>=2.0; extra == 'all'
Provides-Extra: anthropic
Requires-Dist: anthropic>=0.30; extra == 'anthropic'
Provides-Extra: dev
Requires-Dist: mypy>=1.10; extra == 'dev'
Requires-Dist: pytest-asyncio>=0.23; extra == 'dev'
Requires-Dist: pytest-cov>=4.0; extra == 'dev'
Requires-Dist: pytest>=8.0; extra == 'dev'
Requires-Dist: ruff>=0.4; extra == 'dev'
Provides-Extra: langchain
Requires-Dist: langchain-core>=0.2; extra == 'langchain'
Provides-Extra: mcp
Requires-Dist: mcp>=1.0; extra == 'mcp'
Provides-Extra: openai
Requires-Dist: openai>=1.0; extra == 'openai'
Provides-Extra: pydantic
Requires-Dist: pydantic>=2.0; extra == 'pydantic'
